ton_message_body_decoder/__init__.py
ton_message_body_decoder-0.0.2.dist-info/METADATA
ton_message_body_decoder-0.0.2.dist-info/WHEEL
ton_message_body_decoder-0.0.2.dist-info/top_level.txt
ton_message_body_decoder-0.0.2.dist-info/RECORD
