Metadata-Version: 2.2
Name: ton_message_body_decoder
Version: 0.0.2
Summary: ton_message_body_decoder
Home-page: https://github.com/Grommash9/ton_message_body_decoder
Author: Oleksandr Prudnikov
Author-email: prudnikov21@icloud.com
Project-URL: Documentation, https://grommash9.github.io/ton_message_body_decoder/
Project-URL: Source, https://github.com/Grommash9/ton_message_body_decoder
Keywords: cryptocurrency,ton
Classifier: Development Status :: 3 - Alpha
Classifier: Intended Audience :: Developers
Classifier: License :: OSI Approved :: MIT License
Classifier: Programming Language :: Python :: 3.9
Classifier: Programming Language :: Python :: 3.10
Classifier: Programming Language :: Python :: 3.11
Classifier: Programming Language :: Python :: 3.12
Requires-Dist: pytoniq_core
Provides-Extra: test
Requires-Dist: hypothesis; extra == "test"
Requires-Dist: ruff; extra == "test"
Requires-Dist: pyproj; extra == "test"
Requires-Dist: pytest; extra == "test"
Requires-Dist: pytest-cov; extra == "test"
Requires-Dist: pytest-asyncio; extra == "test"
Requires-Dist: tox; extra == "test"
Requires-Dist: build; extra == "test"
Dynamic: author
Dynamic: author-email
Dynamic: classifier
Dynamic: description
Dynamic: description-content-type
Dynamic: home-page
Dynamic: keywords
Dynamic: project-url
Dynamic: provides-extra
Dynamic: requires-dist
Dynamic: summary
